{
  "entityType" : "NOTIFICATION_RULE",
  "entity" : {
    "additionalConfig" : {
      "description" : "Send notification to tenant admins when any Rule chain or Rule node failed to start, update or stop"
    },
    "enabled" : true,
    "externalId" : null,
    "id" : {
      "entityType" : "NOTIFICATION_RULE",
      "id" : "6036c900-7cea-11f0-b07b-3f9331e88cfc"
    },
    "name" : "Rule node initialization failure",
    "recipientsConfig" : {
      "targets" : [ "60284a10-7cea-11f0-b07b-3f9331e88cfc" ],
      "triggerType" : "RULE_ENGINE_COMPONENT_LIFECYCLE_EVENT"
    },
    "templateId" : {
      "entityType" : "NOTIFICATION_TEMPLATE",
      "id" : "6035dea0-7cea-11f0-b07b-3f9331e88cfc"
    },
    "triggerConfig" : {
      "triggerType" : "RULE_ENGINE_COMPONENT_LIFECYCLE_EVENT",
      "onlyRuleChainLifecycleFailures" : true,
      "onlyRuleNodeLifecycleFailures" : true,
      "ruleChainEvents" : [ "UPDATED", "STARTED", "STOPPED" ],
      "ruleChains" : null,
      "ruleNodeEvents" : [ "UPDATED", "STARTED", "STOPPED" ],
      "trackRuleNodeEvents" : true,
      "triggerType" : "RULE_ENGINE_COMPONENT_LIFECYCLE_EVENT"
    },
    "triggerType" : "RULE_ENGINE_COMPONENT_LIFECYCLE_EVENT"
  }
}