{
  "entityType" : "CUSTOMER",
  "entity" : {
    "additionalInfo" : {
      "isPublic" : true
    },
    "address" : null,
    "address2" : null,
    "city" : null,
    "country" : null,
    "customMenuId" : null,
    "customerId" : null,
    "email" : null,
    "externalId" : null,
    "id" : {
      "entityType" : "CUSTOMER",
      "id" : "22851bf0-7da5-11f0-8d06-855ef8580a98"
    },
    "name" : "Public",
    "ownerId" : null,
    "parentCustomerId" : null,
    "phone" : null,
    "state" : null,
    "title" : "Public",
    "zip" : null
  },
  "relations" : [ ],
  "attributes" : {
    "SERVER_SCOPE" : [ ]
  }
}